README.txt
breadcrumbs.py
setup.py
python_breadcrumbs.egg-info/PKG-INFO
python_breadcrumbs.egg-info/SOURCES.txt
python_breadcrumbs.egg-info/dependency_links.txt
python_breadcrumbs.egg-info/top_level.txt