Metadata-Version: 1.0
Name: python-breadcrumbs
Version: 0.1.2
Summary: Store breadcrumbs for later accessing an object internals
Home-page: https://github.com/kaiyou/python-breadcrumbs
Author: Pierre Jaury
Author-email: pierre@jaury.eu
License: GPLv3
Platform: UNKNOWN
